plone.app.folder-1.3.1-py2.7-nspkg.pth
plone/app/folder/__init__.py
plone/app/folder/base.py
plone/app/folder/configure.zcml
plone/app/folder/folder.py
plone/app/folder/migration.py
plone/app/folder/nextprevious.py
plone/app/folder/nogopip.py
plone/app/folder/utils.py
plone/app/folder/tests/__init__.py
plone/app/folder/tests/base.py
plone/app/folder/tests/benchmarks.py
plone/app/folder/tests/content.py
plone/app/folder/tests/layer.py
plone/app/folder/tests/test_integration.py
plone/app/folder/tests/test_migration.py
plone/app/folder/tests/test_nextprevious.py
plone/app/folder/tests/test_partialordering_integration.py
plone/app/folder/tests/test_unorderedordering_integration.py
plone/app/folder/tests/test_utils.py
plone/app/folder/tests/testing.zcml
plone/app/folder/www/index.gif
plone.app.folder-1.3.1.dist-info/METADATA
plone.app.folder-1.3.1.dist-info/WHEEL
plone.app.folder-1.3.1.dist-info/namespace_packages.txt
plone.app.folder-1.3.1.dist-info/top_level.txt
plone.app.folder-1.3.1.dist-info/RECORD
