Metadata-Version: 2.1
Name: plone.app.folder
Version: 1.3.1
Summary: Integration package for `plone.folder` into Plone
Home-page: https://pypi.org/project/plone.app.folder/
Author: Plone Foundation
Author-email: plone-developers@lists.sourceforge.net
License: GPL version 2
Keywords: folder btree order plone archetypes atcontenttypes
Platform: Any
Classifier: Development Status :: 6 - Mature
Classifier: Environment :: Web Environment
Classifier: Framework :: Plone
Classifier: Framework :: Plone :: 5.2
Classifier: Framework :: Zope2
Classifier: Framework :: Zope :: 4
Classifier: Intended Audience :: Developers
Classifier: Intended Audience :: System Administrators
Classifier: Intended Audience :: Other Audience
Classifier: License :: OSI Approved :: GNU General Public License v2 (GPLv2)
Classifier: Operating System :: OS Independent
Classifier: Programming Language :: Python
Classifier: Programming Language :: Python :: 2.7
Classifier: Programming Language :: Python :: 3.6
Classifier: Programming Language :: Python :: 3.7
Classifier: Programming Language :: Python :: 3.8
Requires-Dist: Products.CMFCore
Requires-Dist: Products.GenericSetup
Requires-Dist: Zope2
Requires-Dist: plone.folder
Requires-Dist: setuptools
Requires-Dist: six
Requires-Dist: plone.app.layout
Provides-Extra: atct
Requires-Dist: Products.ATContentTypes ; extra == 'atct'
Requires-Dist: Products.Archetypes ; extra == 'atct'
Requires-Dist: Products.BTreeFolder2 ; extra == 'atct'
Provides-Extra: test
Requires-Dist: plone.app.testing ; extra == 'test'
